swagger_spec_validator/__about__.py
swagger_spec_validator/__init__.py
swagger_spec_validator/common.py
swagger_spec_validator/py.typed
swagger_spec_validator/ref_validators.py
swagger_spec_validator/util.py
swagger_spec_validator/validator12.py
swagger_spec_validator/validator20.py
swagger_spec_validator/schemas/v1.2/apiDeclaration.json
swagger_spec_validator/schemas/v1.2/authorizationObject.json
swagger_spec_validator/schemas/v1.2/dataType.json
swagger_spec_validator/schemas/v1.2/dataTypeBase.json
swagger_spec_validator/schemas/v1.2/infoObject.json
swagger_spec_validator/schemas/v1.2/modelsObject.json
swagger_spec_validator/schemas/v1.2/oauth2GrantType.json
swagger_spec_validator/schemas/v1.2/operationObject.json
swagger_spec_validator/schemas/v1.2/parameterObject.json
swagger_spec_validator/schemas/v1.2/resourceListing.json
swagger_spec_validator/schemas/v1.2/resourceObject.json
swagger_spec_validator/schemas/v2.0/schema.json
swagger_spec_validator-3.0.4.dist-info/LICENSE.txt
swagger_spec_validator-3.0.4.dist-info/METADATA
swagger_spec_validator-3.0.4.dist-info/WHEEL
swagger_spec_validator-3.0.4.dist-info/top_level.txt
swagger_spec_validator-3.0.4.dist-info/RECORD
