Metadata-Version: 2.1
Name: swagger-spec-validator
Version: 3.0.4
Summary: Validation of Swagger specifications
Home-page: http://github.com/Yelp/swagger_spec_validator
Author: Yelp
Author-email: core-services@yelp.com
License: Apache License, Version 2.0
Classifier: Development Status :: 5 - Production/Stable
Classifier: Intended Audience :: Developers
Classifier: Topic :: Software Development :: Libraries :: Python Modules
Classifier: Operating System :: OS Independent
Classifier: Programming Language :: Python :: 3.7
Classifier: Programming Language :: Python :: 3.8
Requires-Python: >=3.8
License-File: LICENSE.txt
Requires-Dist: jsonschema
Requires-Dist: pyyaml
Requires-Dist: typing-extensions
Requires-Dist: importlib-resources>=1.3
